{
"4lr2kncjgiktltw7apn6bn2x":["benjamino2000","Ben O from SLP"],
"e72o6cwcc726bsani2ly6vn6":["brettslp","Brett, MS, CCC-SLP"],
"ewi7d7boubrhy7oxgnlcfuep":["enbyslp","Enby SLP (they/them)"],
"ib3cyrqrub3aciza75cbalez":["lkbutler","Lindsay Butler, PhD, CCC-SLP"],
"y3f3oa4cbudcyiqkh5v75zpc":["rpgslp","RfP the RPG SLP"],
"wkrynyy3hff24gssz6lydng3":["slpsummer","SLP Summer"],
"jondheoeqaiyukw5lvoeq7qo":["slpaquette","Season"],
"tlti5bctlnvjmkkfuitoss73":["slphr","layla"],
"mcv6aysc6idtkwd7fnrssabu":["slptanya","SLPTanya"],
"kvnnguvkyrqbjic6yr3cv5zq":"slphilxyz",
"nb34tkp32544xwwjt3id62f4":["sleepyy","slpy"],
"2oscrtibzkz2miixlaiy3xiv":"slp",
"5u6qonjmcedu45iijok64v3w":["slpeter","Peter Meulenbroek "],
"grf5atkcg3z34swnng6blknr":["slpierce111","Sarah Don't Care-ah"],
"ozrrrk75ivogm76m5ozjcdrp":"slpmhkhkshow",
"y4siugpyq3xyf6jik7aes54p":["slpaustin","Austin Thompson"],
"wrni5ebeevtsz2oys375xqrm":["slpng-giants-fr","Sleeping Giants FR"],
"vyk2xfcf5cu3ds5phnfiq33o":["slpdprvdtchy","Sleepdeprivedtechie"],
"scltoggeafpf675k76axlgyi":["slplu","sleeplu.alt"],
"rguehahlga6qc72vguw2yjvf":"slpancakes",
"knqdfjhpb5jamjrh3lvuj53q":"slperez",
"hwrquipt3hzly7nxj4272urr":"slppyclwn",
"lbcydewnnhrfyypbr5hyyof5":["slplc","Simon"],
"rvmtmqyufc5zf5wwaa2sx7qn":"slpwlkng",
"nf4a2amzm67dvlwsgw474s2x":["slpyjoe54","Telerwief"],
"7xyq5iwf2wmufl27ftjlwpxw":["spslpslt","Sepehr Slp 👓"],
"7vapjjuyshjmbmwsekwcwryu":["theinformedslp","The Informed SLP"]
}
