{
"4m7r6yi3cmeteari3iuamopc":["9sypher","Mas "],
"a7zvzcmpk4um5wrlg2vleeis":["asypniew","Aaron Sypniewski "],
"rkrg7m32e44awgpbxwk44cri":["doubledinner","Seth Sypko"],
"zvgtbzqmaavjm6zeqiulrri3":["ecribouille","Syphaïwong Bay"],
"4eixeqo6b5ajopdml5zis7wn":["esypek","Elizabeth Sypek"],
"yd53pz2jacfo7g5alq6rrxqz":["goldsipa","Pavlo Sypyhin "],
"fnxivz5xi4aqrwlhrccxod46":["horusiath","Bartosz Sypytkowski"],
"lzoljdfq6kes2kuhbtxyakv2":["moraymalice","Syphe 🏳️‍⚧️"],
"bbdsdompcmafyndvhgb6pgcn":["notsyphforwork","NotSyph"],
"wakmzz2ifndez7q5xdru6hqy":["simplysyps","Syps!!"],
"72jdv4a4nrvzdi2uxxlvgrq6":["syphilia","Syphilia Morgenstierne"],
"hlo5533k33inoivgqd64abp3":["sypher","Sypher"],
"sqzfsppbgwzj6aauvmhoofna":["sypanda","Sy Pando"],
"vnmqj2qhzuwgsmk7wldx2jf3":["syphrosyn","Syph ⚜ Catboy Haven"],
"cdhwsujcvparnsy7q6qafbgu":"sypsos",
"kpaq2halqtjs4u5h65wal7uu":["syphon","Syphon"],
"6j4u7o3mcujzw5k6cmdzs2xx":"syppy",
"kk3jrp4efhf2jdcxhcbknsr3":["syphilitic","syphilitic chicken"],
"d5znm5eagb5f4l24626mssci":["sypha1","Jamie"],
"bwmnlysadqesa6wvcb4hjpta":["syp3boc1102usg","さやぴꔛ"],
"qmxnxenpjl2mbgcendmcg3b2":["syp","yo spooky mama"],
"7eittgzlvsuo62tdsrdpmqcu":"syphini",
"cq2coyapj3aqadqkzesyf5qr":["sypster","Syp"],
"kamz5knzhjoissqolei427zc":["syphorel","Syphorel"],
"cffonyjlflxfdfn2cqqjevvp":["syppu","Syyppu"],
"zwli3spilph3vekz6gkivs3l":["syphiki","Datura"],
"a4swowszar3dmpurzjgt4fty":"sypher0131",
"haojgn6fn6xfnqz2v6kdpbyc":"sypher01323",
"ocuc7dg3gp32nzqvnkvaw3a6":"syphi",
"3kfgjdsc5bs5rwdh5n43sszw":["sypsoti","Sypsoti"],
"lnrfd6hw37xxq57ujtjszvsn":["syphonactual","SyphonActual"],
"7wyckxbg4rf6qb7xnori4pf6":"sypher01316",
"4y55y2wzailossc2w7ao2iog":["sypolt","Greg Sypolt"],
"5cpmudkbfo4b45wtk37lvxfq":"sypher01315",
"4xlbzk74bk5v5xy2xtrl6tlo":["syphonchee","Syphon"],
"qtrwyqfecfzbov4c7it6hcpb":["syparasie","Sylvain Parasie "],
"l2dymoj6c37eb4jyj666nrpb":"sypharbeit",
"jx5bmrwxlq26it7mct7mcwr2":["syphere","Syphere"],
"bdjzxgvm2ano5er2qzofbunq":["sypazarix","Sy"],
"hfbifa35wrkjo24aryfhvxxd":["syphrus","Syphrus"],
"gj2cfmy7wnfaf5fvy4ugbarv":["syphotic","Syphotic"],
"6xafeggrvuw7zt5ra5aq6ksl":["sypp76","Sypp76 🩺"],
"fei6xkkpg673u6pgvt76to4d":"sypria",
"jaqivxiukcejthodiwohmjij":["syphilas","Silas ☭"],
"h6qjvn2ypxay457wf2cenufv":["syphari","Syphari"],
"6ulk2hty2ue3owrvgh3dsc2a":"sypress",
"jlbrwwbelo2zllfnrjcem647":["syprold","Syprold"],
"aufo24xljx6elby7xirqvjzq":"sypz2552",
"azkg3jx7pnvh3zfu66ri6azd":["syphirra","Ruby 💕"],
"wtnhvm4i3rjxltcz665n6l7k":"sypk",
"v2bdkp457y2qaas2dho6tudb":["syphthegoblin","Syph the Gob"],
"s2pnkxzvabmvk63dej4us5f7":["sypph","SYP in der AG Public History "],
"j3gvjzjkoxyxzjta76sv77fj":["tabulararc74","Syprus"],
"yjr7yvbpyvy7pp6frgaaioea":["zeeshypnosis","Zee Sype"],
"s7adjeblvamlnjfosojvkt2s":["sypiiix","SyPiiiX"]
}
