{
"jid6ylq57abr4s4tnpkf5wbx":["enmw4now","sdfvg"],
"efnqtlxelnvecm7jytkbdspq":"fgh6sdff7sfg6",
"tcudvhle7uxd73z3aq6lhqa2":["poisujdehfpsdf","sdfasdfasdf"],
"jdu4etfyvvogbtqbitlgxdwi":["sdfstu","Stu F."],
"nlnuomtqob4oxyz433gjwo2m":["sdfg158","みやさん"],
"vhvlohovyyrxheoykb2ilepc":["sdfield","isa!!! ☆"],
"7ipma6qm5xybfi2ulhsu7gdz":["sdfrederiksen","Soren Frederiksen"],
"qyqutkg5zwtmrtyom2hirovh":["sdfffffdf","sdfsdf"],
"sqjkornj4pohkidvdxkfuc7h":["sdfstudios","Shiv"],
"kkrwyn77ean2hlblcdtwvo3n":["sdfilmcritic","Dallas Jay"],
"kcvseepiedacvd6i3d53y775":"sdflickinger",
"quqdcrhqsuwgctggm6yro25l":"sdf",
"ctv3yt4lf3z7qtn6lgjzl6th":["sdfnico","Nico plays Train Game"],
"qao7uhgbalcxthhe64ek4m7a":["sdfgiyrdb","نفس "],
"s4rdkhhwdjdrepxiiu3axd62":["sdfoik-author","s.d.foik"],
"45ilzzq72qaitebfb35druh2":["sdfrankowski","Scott Frankowski"],
"nu5h3ac2d7quqh3jd7fnzoyz":["sdfgoodall","SDFG"],
"4wnjsm4trrgrx5ys362fjwaz":"sdfsdf",
"uq6mpl3sofjxvgqpqe5jzlgj":"sdfsdfd",
"35tcl5bqm5v7rcsthroimqvi":"sdfairbank",
"jpyypca2iwvs2oyeskoj5t2e":["sdforg","SDF"]
}
