{
"huzauakpzazyqshvcqq3mbnf":["matchasrgl","MatchaSrgl🔜BLFC'23🎲"],
"dvykoebsla5iqyezyu3ujpfi":["sethgitter","srgitter"],
"4ezj4vucfm3frqyqsf7ahaf4":["srgower","Stephen Gower"],
"cngmxulwkyiptfucaewyksxd":["srg-wtf","Comrade Stephanie "],
"g7ssjxedthahb22oquf2np2t":["srgreja","GreJa"],
"jcgdp3oyqydkuexxmol3r5ho":["srgk","Serhii"],
"klazaktpbps7eyftcwzzf3nb":["srganuch","Savanna Ganucheau"],
"lnijdrxkad4i57egwb6uxvhn":["srgts","Giant Sam 🔞"],
"wdppeyxbwrexnhyyqffgvlng":["srglobal","Ewerton Azevedo 🎓🐈‍⬛ "],
"z6uncvyibobzibh324ifr6tj":["srge0","Mr. Br "],
"57iqljld74accrzz3r3dncfd":["srgaudette","Sarah Roth-Gaudette"],
"ze3hgsas56fwmanvo25omf4a":["srgche","П'яна ботоферма дядька Мілнера "],
"wscnw2noiicrixpk2565uyi5":["srgio","Sergio"],
"72pgae4ccuynyxlxluauyhj2":["srgalloway","Samuel R Galloway"],
"xmdg4fbt5ktsy3pccxyxttgl":["srgarou","Sr. Garou"],
"5jgx36zhbr62pbjo5hsylpuv":["srgordon","SR Gordon "],
"lv4xwyesow3owy2xwz5flg2a":["srgr0.com","Srgr0"],
"ymoc3qg42xjgovr23wklw2ch":["srgntr","Sergonator"],
"lkl6gjaajloopx5h3vhfnsuu":["srg","駿河"],
"bmzufrpt53poh77e4jnkfofm":["srgnation","SRGNation"],
"5hfw7i4toyjg7m2ygmaczdhd":["srg48","Sr.G"],
"w5qkmnuii67isouygs42snwn":["srgisme","Grzegorz Brzęczyszczykiewicz (Stefan)"],
"nxlvllpbbhrkd463qajmb5xx":"srganzer",
"etkthm23fqjjbub3442tbf6q":["srguillermo","Guillermo"],
"qvnclddwzcragqfbunpc7hbi":"srgoes",
"vgat75ymonh4d37ypmmo63bo":["srgriffithauthor","S.R. Griffith | Author | New PNR Release"],
"ifyjaqx3y5r6ygyeu7gkkame":"srgluigi",
"2fah7qxln6rlgs4gbuewmyv3":["srgoyis","Sr Goyis"],
"2mabkrtglqpa3knogucietxp":["srgesus","SrGesus"],
"q4kpxudbfml2nu7poh4dwv6z":"srg404",
"vtfbqkidtb3vuplt5hqovrvt":["srgonzalez","Sara Gonzalez"],
"kmeey344lzmkeqfeho6wlbxb":["srgb88","Sérgio Brandão"],
"f2t4gr6nyr7vghjfgalzza7g":["srgutinho","Gutinho"],
"k6l6wcssskmib7dd6l5ykr5l":["srgtmeow","Kodi "],
"7slfymnekzszaq6dmip76wlp":["srgnfri","Douglas"],
"guilhwrrghxphxazekhjvb25":["srgwrk","SuRge"],
"sjrlfodovi235wyd4u3g5xua":["srglaciesart","Sr.Glacies"],
"qmr6vexg5nvycr3zwquzonww":"srgarcia",
"qjwqdaqxqupimtnollcqfja6":"srgriffin",
"efkob3a7upwfxh5ikpjmahk4":"srgeek",
"sx44izmhdczuzz7hkm6pg4nf":"srgtlaplante",
"wksmkqhhyuddyqq3de6p2lhj":["srgonzzalez","P."],
"42gq33wnrgshfvgo26effyc6":"srggil",
"jjp57yr5av2aaxq63kqle2tc":["srgit","Srgit"],
"fihkzq7kffpuf6elg3ahfklk":"srgacdc",
"q756la6svwfpoaqmrm3tmqz5":["srgiancar","SrGiancar"],
"hdt3dxkf6fz2y4htpo4rzias":["srgp","Rivkah"],
"xyln4f4x22z4ln5ymc7keak5":"srgt",
"ctrmdmipecgpodx2qqahfvea":["suborak","SrglMerp"]
}
